gpytorch_lattice_kernel/__init__.py
gpytorch_lattice_kernel/bilateral_kernel.py
gpytorch_lattice_kernel/lattice_test.py
gpytorch_lattice_kernel/cpp/lattice.cpp
gpytorch_lattice_kernel/cpp/permutohedral.h
gpytorch_lattice_kernel/cuda/permutohedral_cuda.cpp
gpytorch_lattice_kernel/cuda/permutohedral_cuda_kernel.cu
gpytorch_lattice_kernel-0.0.dev1.dist-info/LICENSE
gpytorch_lattice_kernel-0.0.dev1.dist-info/METADATA
gpytorch_lattice_kernel-0.0.dev1.dist-info/WHEEL
gpytorch_lattice_kernel-0.0.dev1.dist-info/top_level.txt
gpytorch_lattice_kernel-0.0.dev1.dist-info/RECORD
