Metadata-Version: 2.1
Name: gpytorch-lattice-kernel
Version: 0.0.dev1
Summary: Lattice kernel for scalable Gaussian processes in GPyTorch
Home-page: https://github.com/activatedgeek/simplex-gp
License: Apache License 2.0
Platform: UNKNOWN
Classifier: Intended Audience :: Developers
Classifier: Intended Audience :: Science/Research
Classifier: License :: OSI Approved :: Apache Software License
Classifier: Programming Language :: Python :: 3.9
Classifier: Topic :: Scientific/Engineering :: Artificial Intelligence
Requires-Python: >=3.6, <4
License-File: LICENSE
Requires-Dist: numpy
Requires-Dist: torch
Requires-Dist: gpytorch
